{
  "updated_at": "2026-05-17T17:56:08.486599+00:00",
  "active_limit": 1660,
  "counts": {
    "poslovanje": 175,
    "ekonomija": 23,
    "financije": 148,
    "trzista": 154,
    "kultura": 179,
    "dizajn": 103,
    "tehnologija": 182,
    "znanost": 151,
    "lifestyle": 120,
    "hedonizam": 13,
    "satovi": 43,
    "nakit": 49,
    "pica": 69,
    "vijesti": 0
  },
  "labels": {
    "poslovanje": "POSLOVANJE",
    "ekonomija": "EKONOMIJA",
    "financije": "FINANCIJE",
    "trzista": "TRŽIŠTA",
    "kultura": "KULTURA",
    "dizajn": "DIZAJN",
    "tehnologija": "TEHNOLOGIJA",
    "znanost": "ZNANOST",
    "lifestyle": "LIFESTYLE",
    "hedonizam": "HEDONIZAM",
    "satovi": "SATOVI",
    "nakit": "NAKIT",
    "pica": "PIĆA",
    "vijesti": "VIJESTI",
    "muzeji": "MUZEJI",
    "galerije": "GALERIJE",
    "umjetnici": "UMJETNICI",
    "umjetnine": "UMJETNINE",
    "film": "FILM",
    "arhitektura": "ARHITEKTURA",
    "umjetnost": "UMJETNOST",
    "putovanja": "PUTOVANJA",
    "symbol": "SYMBOL"
  }
}