[
  {
    "title": "ANTENA ZAGREB",
    "country": "HRVATSKA",
    "description": "Hrvatski glazbeni i informativni radio. Player pokušava direktni stream, a ako vanjski servis blokira reprodukciju koristi gumb za službenu stranicu.",
    "stream": "https://playerservices.streamtheworld.com/api/livestream-redirect/ANTENAZAGREB.mp3",
    "streams": [
      "https://playerservices.streamtheworld.com/api/livestream-redirect/ANTENAZAGREB.mp3",
      "https://playerservices.streamtheworld.com/api/livestream-redirect/ANTENAZAGREB_SC"
    ],
    "site": "https://www.antenazagreb.hr/"
  },
  {
    "title": "TOP RADIO",
    "country": "HRVATSKA",
    "description": "Hrvatski glazbeni radio iz Zagreba. Ako direktni stream ne krene, otvori službenu stranicu.",
    "stream": "https://playerservices.streamtheworld.com/api/livestream-redirect/TOPRADIO.mp3",
    "streams": [
      "https://playerservices.streamtheworld.com/api/livestream-redirect/TOPRADIO.mp3",
      "https://playerservices.streamtheworld.com/api/livestream-redirect/TOPRADIO_SC"
    ],
    "site": "https://topradio.hr/"
  },
  {
    "title": "LAGANINI FM",
    "country": "HRVATSKA",
    "description": "Hrvatski glazbeni radio. Dodano kao alternativa Otvorenom i Narodnom.",
    "stream": "https://stream.laganini.fm/laganini",
    "streams": [
      "https://stream.laganini.fm/laganini",
      "https://c5.hostingcentar.com:8059/stream"
    ],
    "site": "https://laganini.fm/"
  },
  {
    "title": "HRT HR 1",
    "country": "HRVATSKA",
    "description": "Hrvatski radio 1. program — informativni i opći program Hrvatske radiotelevizije.",
    "stream": "https://playerservices.streamtheworld.com/api/livestream-redirect/PROGRAM1.mp3",
    "streams": [
      "https://playerservices.streamtheworld.com/api/livestream-redirect/PROGRAM1.mp3"
    ],
    "site": "https://radio.hrt.hr/prvi-program"
  },
  {
    "title": "BBC WORLD SERVICE",
    "country": "UK / INTERNATIONAL",
    "description": "Međunarodni informativni radio na engleskom jeziku.",
    "stream": "https://stream.live.vc.bbcmedia.co.uk/bbc_world_service",
    "streams": [
      "https://stream.live.vc.bbcmedia.co.uk/bbc_world_service"
    ],
    "site": "https://www.bbc.com/audio"
  },
  {
    "title": "FRANCEINFO",
    "country": "FRANCUSKA",
    "description": "Francuski informativni radio stream.",
    "stream": "https://icecast.radiofrance.fr/franceinfo-midfi.mp3",
    "streams": [
      "https://icecast.radiofrance.fr/franceinfo-midfi.mp3"
    ],
    "site": "https://www.francetvinfo.fr/replay-radio/direct"
  }
]
